{
  "date": "2026-02-27",
  "picks": [
    {
      "종목명": "한국항공우주",
      "티커": "047810.KS",
      "섹터": "조선/방산",
      "종가": 191200,
      "점수": 57
    },
    {
      "종목명": "LG에너지솔루션",
      "티커": "373220.KS",
      "섹터": "2차전지",
      "종가": 425000,
      "점수": 56
    },
    {
      "종목명": "카카오",
      "티커": "035720.KS",
      "섹터": "IT/플랫폼",
      "종가": 63200,
      "점수": 55
    },
    {
      "종목명": "에코프로",
      "티커": "086520.KQ",
      "섹터": "2차전지",
      "종가": 183100,
      "점수": 52
    },
    {
      "종목명": "삼성SDI",
      "티커": "006400.KS",
      "섹터": "2차전지",
      "종가": 458750,
      "점수": 52
    },
    {
      "종목명": "삼성에스디에스",
      "티커": "018260.KS",
      "섹터": "IT/플랫폼",
      "종가": 192200,
      "점수": 52
    },
    {
      "종목명": "카카오페이",
      "티커": "377300.KQ",
      "섹터": "IT/플랫폼",
      "종가": 68300,
      "점수": 52
    },
    {
      "종목명": "현대제철",
      "티커": "004020.KS",
      "섹터": "자동차",
      "종가": 41550,
      "점수": 51
    },
    {
      "종목명": "기아",
      "티커": "000270.KS",
      "섹터": "자동차",
      "종가": 202000,
      "점수": 51
    },
    {
      "종목명": "현대차",
      "티커": "005380.KS",
      "섹터": "자동차",
      "종가": 608000,
      "점수": 51
    }
  ]
}